Topsis_Vaibhav_102003423/Vaibhav_102003423.py
Topsis_Vaibhav_102003423-0.2.dist-info/LICENSE.txt
Topsis_Vaibhav_102003423-0.2.dist-info/METADATA
Topsis_Vaibhav_102003423-0.2.dist-info/WHEEL
Topsis_Vaibhav_102003423-0.2.dist-info/entry_points.txt
Topsis_Vaibhav_102003423-0.2.dist-info/top_level.txt
Topsis_Vaibhav_102003423-0.2.dist-info/RECORD
