Metadata-Version: 2.1
Name: Topsis-Vaibhav-102003423
Version: 0.2
Summary: Doing Evaluation of alternatives based on multiple criteria using TOPSIS method.
Author: Vaibhav Verma
Author-email: vverma_be20@thapar.edu
Classifier: Programming Language :: Python :: 3
Classifier: License :: OSI Approved :: MIT License
Classifier: Operating System :: OS Independent
License-File: LICENSE.txt
Requires-Dist: pandas
